{
  "modelo": "pymc_binomial_jerarquico",
  "timestamp": "2026-04-19T19:35:00+00:00",
  "snapshot_panel": "district_panel.csv",
  "n_distritos_usados": 1871,
  "votos_contados_Sanchez": 1876706,
  "votos_contados_LA": 1821844,
  "votos_pendientes_estimados": 909939,
  "votos_pend_normal": 0,
  "votos_pend_jee": 909939,
  "jee_total_nacional": 5242,
  "jee_por_departamento": {
    "LIMA": 1396,
    "PIURA": 428,
    "LORETO": 416,
    "LA LIBERTAD": 382,
    "ÁNCASH": 257,
    "CAJAMARCA": 239,
    "ICA": 228,
    "HUÁNUCO": 204,
    "UCAYALI": 184,
    "JUNÍN": 171
  },
  "jee_taxonomia": {
    "razones_top": [
      [
        "Acta con error aritmético",
        3854
      ],
      [
        "Acta sin firmas",
        358
      ],
      [
        "Acta con error aritmético, Acta ilegible",
        320
      ],
      [
        "Acta impugnada",
        311
      ],
      [
        "Acta con error aritmético, Acta impugnada",
        86
      ],
      [
        "Acta con error aritmético, Acta sin firmas",
        54
      ],
      [
        "Acta ilegible",
        33
      ],
      [
        "Acta incompleta",
        32
      ],
      [
        "Acta incompleta, Acta sin firmas",
        26
      ],
      [
        "Otras",
        18
      ]
    ],
    "locales_top": [
      {
        "distrito": "CASTILLA",
        "local": "UNIVERSIDAD NACIONAL DE PIURA - UNP",
        "actas_obs": 15
      },
      {
        "distrito": "SANTIAGO DE SURCO",
        "local": "IE 6082 LOS PROCERES",
        "actas_obs": 10
      },
      {
        "distrito": "SAN JUAN DE MIRAFLORES",
        "local": "IE 6038 OLLANTAY",
        "actas_obs": 10
      },
      {
        "distrito": "BELÉN",
        "local": "IE 60993 RAMON CASTILLA Y MARQUESADO",
        "actas_obs": 9
      },
      {
        "distrito": "VIRÚ",
        "local": "IE 80074 MARIA CARIDAD AGUERO DE ARRESSE",
        "actas_obs": 9
      },
      {
        "distrito": "VEINTISÉIS DE OCTUBRE",
        "local": "IE 14008 LEONOR CERNA DE VALDIVIEZO",
        "actas_obs": 8
      },
      {
        "distrito": "CALLERIA",
        "local": "IE EMBLEMATICA 64753 FAUSTINO MALDONADO",
        "actas_obs": 8
      },
      {
        "distrito": "SAN JUAN DE MIRAFLORES",
        "local": "IE FE Y ALEGRIA 65",
        "actas_obs": 8
      },
      {
        "distrito": "LOS BAÑOS DEL INCA",
        "local": "IE 82040 VIRGEN DE LA NATIVIDAD",
        "actas_obs": 8
      },
      {
        "distrito": "CIENEGUILLA",
        "local": "IE JESUS SACRAMENTADO",
        "actas_obs": 8
      }
    ],
    "horas_digitalizacion": {
      "00": 423,
      "01": 235,
      "02": 202,
      "03": 84,
      "04": 98,
      "05": 80,
      "06": 65,
      "07": 98,
      "08": 95,
      "09": 105,
      "10": 109,
      "11": 167,
      "12": 180,
      "13": 183,
      "14": 147,
      "15": 149,
      "16": 163,
      "17": 126,
      "18": 119,
      "19": 95,
      "20": 88,
      "21": 306,
      "22": 484,
      "23": 549
    },
    "flash_lt_30s": 1,
    "nocturno_2_5am": 464,
    "total_scrapeadas": 5104
  },
  "prediccion": {
    "Sanchez": {
      "candidato": "Sanchez",
      "media": 1993742.983,
      "mediana": 1993080.0,
      "ci_low": 1967598.9,
      "ci_high": 2023911.025
    },
    "LA": {
      "candidato": "LA",
      "media": 1912750.838,
      "mediana": 1911545.5,
      "ci_low": 1888643.025,
      "ci_high": 1939982.1
    },
    "diferencia_Sanchez_minus_LA": {
      "mediana": 80939.5,
      "ci_low": 73816.85,
      "ci_high": 88905.1
    },
    "P(Sanchez > LA)": 1.0
  },
  "sampler": {
    "draws": 500,
    "tune": 500,
    "chains": 2,
    "likelihood": "BetaBinomial (con overdispersion kappa)",
    "rhat_max_sanchez": 1.05,
    "rhat_max_la": 1.01,
    "kappa_mean_sanchez": 59.4576734574717,
    "kappa_mean_la": 170.0880878030949,
    "tiempo_segundos": 261.5
  },
  "econometria": {
    "covariables": [
      "altitud_km_z",
      "idh_z",
      "pobreza_z",
      "log_densidad_z",
      "vuln_alim_z"
    ],
    "beta_2021": {
      "Sanchez": {
        "mediana": -0.064440654165435,
        "ci_low": -0.11130224915350576,
        "ci_high": -0.022478834270667675,
        "sign_cert": 0.996
      },
      "LA": {
        "mediana": 0.342402127850724,
        "ci_low": 0.29030123344958847,
        "ci_high": 0.39801186497444885,
        "sign_cert": 1.0
      }
    },
    "gamma": {
      "Sanchez": {
        "altitud_km_z": {
          "mediana": 0.007268984056513262,
          "ci_low": -0.037949409520561465,
          "ci_high": 0.05260401169409947,
          "sign_cert": 0.628
        },
        "idh_z": {
          "mediana": -0.1317475444464801,
          "ci_low": -0.2019146611425677,
          "ci_high": -0.05908496376676465,
          "sign_cert": 1.0
        },
        "pobreza_z": {
          "mediana": 0.2212506404201216,
          "ci_low": 0.16864596526832995,
          "ci_high": 0.27677256509949544,
          "sign_cert": 1.0
        },
        "log_densidad_z": {
          "mediana": -0.09174201084141423,
          "ci_low": -0.12689161609245336,
          "ci_high": -0.058868119829943714,
          "sign_cert": 1.0
        },
        "vuln_alim_z": {
          "mediana": 0.28894088244804783,
          "ci_low": 0.2107710083620688,
          "ci_high": 0.3691697770012235,
          "sign_cert": 1.0
        }
      },
      "LA": {
        "altitud_km_z": {
          "mediana": -0.07014860069127621,
          "ci_low": -0.11031161015640634,
          "ci_high": -0.03202297596580572,
          "sign_cert": 1.0
        },
        "idh_z": {
          "mediana": 0.18099851975469744,
          "ci_low": 0.1157092514391395,
          "ci_high": 0.2548065334394616,
          "sign_cert": 1.0
        },
        "pobreza_z": {
          "mediana": -0.20266271893485877,
          "ci_low": -0.25573052161788135,
          "ci_high": -0.1389081601107745,
          "sign_cert": 1.0
        },
        "log_densidad_z": {
          "mediana": 0.09934458105666827,
          "ci_low": 0.06707900673868303,
          "ci_high": 0.12548390234476506,
          "sign_cert": 1.0
        },
        "vuln_alim_z": {
          "mediana": 0.11628351257842069,
          "ci_low": 0.039134419607201924,
          "ci_high": 0.19371866988421668,
          "sign_cert": 0.999
        }
      }
    }
  }
}